django_bookstack/__init__.py
django_bookstack/admin.py
django_bookstack/apps.py
django_bookstack/models.py
django_bookstack/tests.py
django_bookstack/urls.py
django_bookstack/views.py
django_bookstack/bookstack/__init__.py
django_bookstack/bookstack/api.py
django_bookstack/bookstack/utils.py
django_bookstack/migrations/__init__.py
django_bookstack/templates/django_bookstack/bookstack_wrapper.html
django_bookstack/templatetags/__init__.py
django_bookstack/templatetags/bookstack.py
django_bookstack-0.0.3.data/data/bookstack_wrapper.html
django_bookstack-0.0.3.dist-info/LICENSE
django_bookstack-0.0.3.dist-info/METADATA
django_bookstack-0.0.3.dist-info/WHEEL
django_bookstack-0.0.3.dist-info/top_level.txt
django_bookstack-0.0.3.dist-info/RECORD
